EULA.md
MANIFEST.in
README.md
README.rst
setup.py
pychronos/__init__.py
pychronos/annotation.py
pychronos/base.py
pychronos/chronos.py
pychronos/collection.py
pychronos/data.py
pychronos/dtype.py
pychronos/exceptions.py
pychronos/freq.py
pychronos/index.py
pychronos/init.py
pychronos/space.py
pychronos/timeseries.py
pychronos/utils.py
pychronos/utils_pandas.py
pychronos/vintage.py
pychronos.egg-info/PKG-INFO
pychronos.egg-info/SOURCES.txt
pychronos.egg-info/dependency_links.txt
pychronos.egg-info/requires.txt
pychronos.egg-info/top_level.txt
pychronos/vendor/openapi_client/__init__.py
pychronos/vendor/openapi_client/api_client.py
pychronos/vendor/openapi_client/configuration.py
pychronos/vendor/openapi_client/exceptions.py
pychronos/vendor/openapi_client/rest.py
pychronos/vendor/openapi_client/api/__init__.py
pychronos/vendor/openapi_client/api/annotations_api.py
pychronos/vendor/openapi_client/api/api_key_api.py
pychronos/vendor/openapi_client/api/collection_api.py
pychronos/vendor/openapi_client/api/group_api.py
pychronos/vendor/openapi_client/api/permissions_api.py
pychronos/vendor/openapi_client/api/raw_annotations_api.py
pychronos/vendor/openapi_client/api/raw_api_key_api.py
pychronos/vendor/openapi_client/api/raw_collection_api.py
pychronos/vendor/openapi_client/api/raw_group_api.py
pychronos/vendor/openapi_client/api/raw_space_api.py
pychronos/vendor/openapi_client/api/raw_time_series_api.py
pychronos/vendor/openapi_client/api/raw_time_series_data_api.py
pychronos/vendor/openapi_client/api/raw_upload_api.py
pychronos/vendor/openapi_client/api/raw_user_api.py
pychronos/vendor/openapi_client/api/raw_vintage_api.py
pychronos/vendor/openapi_client/api/space_api.py
pychronos/vendor/openapi_client/api/time_series_api.py
pychronos/vendor/openapi_client/api/time_series_data_api.py
pychronos/vendor/openapi_client/api/user_api.py
pychronos/vendor/openapi_client/api/vintage_api.py
pychronos/vendor/openapi_client/models/__init__.py
pychronos/vendor/openapi_client/models/action.py
pychronos/vendor/openapi_client/models/aid.py
pychronos/vendor/openapi_client/models/annotation.py
